trantor/__init__.py
trantor-0.1.0.dist-info/WHEEL
trantor-0.1.0.dist-info/entry_points.txt
trantor-0.1.0.dist-info/METADATA
trantor-0.1.0.dist-info/RECORD
